sicheng_demo/__init__.py
sicheng_demo/say_hello.py
sicheng_demo-0.1.0.dist-info/METADATA
sicheng_demo-0.1.0.dist-info/WHEEL
sicheng_demo-0.1.0.dist-info/RECORD
