Metadata-Version: 2.1
Name: sicheng-demo
Version: 0.1.0
Summary: 
Author: sicheng1806
Author-email: sicheng1806@outlook.com
Requires-Python: >=3.12,<4.0
Classifier: Programming Language :: Python :: 3
Classifier: Programming Language :: Python :: 3.12
Requires-Dist: numpy (>=1.26.4,<2.0.0)
